splitit_client/__init__.py
splitit_client/api_client.py
splitit_client/api_response.py
splitit_client/client.py
splitit_client/configuration.py
splitit_client/exceptions.py
splitit_client/exceptions_base.py
splitit_client/request_after_hook.py
splitit_client/request_before_hook.py
splitit_client/rest.py
splitit_client/schemas.py
splitit_client/validation_metadata.py
splitit_client/apis/__init__.py
splitit_client/apis/path_to_api.py
splitit_client/apis/tag_to_api.py
splitit_client/apis/paths/__init__.py
splitit_client/apis/paths/api_data_get_countries.py
splitit_client/apis/paths/api_data_get_currencies.py
splitit_client/apis/paths/api_data_get_processors.py
splitit_client/apis/paths/api_data_get_verticals.py
splitit_client/apis/paths/api_data_status_legend.py
splitit_client/apis/paths/api_merchants_create.py
splitit_client/apis/paths/api_merchants_create_developer.py
splitit_client/apis/paths/api_merchants_get.py
splitit_client/apis/paths/api_merchants_get_details.py
splitit_client/apis/tags/__init__.py
splitit_client/apis/tags/data_api.py
splitit_client/apis/tags/merchants_api.py
splitit_client/model/__init__.py
splitit_client/model/countries_response.py
splitit_client/model/country_response.py
splitit_client/model/create_developer_request.py
splitit_client/model/create_merchant_request.py
splitit_client/model/create_merchant_response.py
splitit_client/model/currencies_response.py
splitit_client/model/currency_response.py
splitit_client/model/enum_dto.py
splitit_client/model/error.py
splitit_client/model/get_merchant_details_response.py
splitit_client/model/get_merchant_response.py
splitit_client/model/get_merchants_response.py
splitit_client/model/merchant_vertical_response.py
splitit_client/model/merchant_verticals_response.py
splitit_client/model/processor_authentication_parameters_request.py
splitit_client/model/processor_response.py
splitit_client/model/processors_response.py
splitit_client/model/request_header_slim.py
splitit_client/model/response_header.py
splitit_onboarding_python_sdk-3.0.0.dist-info/LICENSE
splitit_onboarding_python_sdk-3.0.0.dist-info/METADATA
splitit_onboarding_python_sdk-3.0.0.dist-info/WHEEL
splitit_onboarding_python_sdk-3.0.0.dist-info/top_level.txt
splitit_onboarding_python_sdk-3.0.0.dist-info/RECORD
