Metadata-Version: 2.1
Name: splitit-onboarding-python-sdk
Version: 3.0.0
Summary: Splitit.OnBoarding.Api.V2
Home-page: https://github.com/konfig-dev/splitit-onboarding-sdks/tree/main/python
Author: Konfig
Author-email: engineering@konfigthis.com
Keywords: OpenAPI,Konfig,Splitit.OnBoarding.Api.V2
Requires-Python: >=3.7
License-File: LICENSE
Requires-Dist: certifi (>=2022.12.7)
Requires-Dist: frozendict (~=2.3.4)
Requires-Dist: python-dateutil (~=2.7.0)
Requires-Dist: setuptools (>=21.0.0)
Requires-Dist: typing-extensions (~=4.3.0)
Requires-Dist: urllib3 (~=1.26.7)
Requires-Dist: validators (~=0.20.0)
